iam/__init__.py
iam/__version__.py
iam/cache.py
iam/collection.py
iam/dummy_iam.py
iam/exceptions.py
iam/iam.py
iam/meta.py
iam/objects.py
iam/shortcuts.py
iam/utils.py
iam/api/__init__.py
iam/api/client.py
iam/api/http.py
iam/apply/__init__.py
iam/apply/models.py
iam/auth/__init__.py
iam/auth/models.py
iam/contrib/__init__.py
iam/contrib/http.py
iam/contrib/converter/__init__.py
iam/contrib/converter/base.py
iam/contrib/converter/queryset.py
iam/contrib/converter/sql.py
iam/contrib/django/__init__.py
iam/contrib/django/middlewares.py
iam/contrib/django/response.py
iam/contrib/django/dispatcher/__init__.py
iam/contrib/django/dispatcher/dispatchers.py
iam/contrib/django/dispatcher/exceptions.py
iam/contrib/iam_migration/__init__.py
iam/contrib/iam_migration/apps.py
iam/contrib/iam_migration/conf.py
iam/contrib/iam_migration/constants.py
iam/contrib/iam_migration/exceptions.py
iam/contrib/iam_migration/migrator.py
iam/contrib/iam_migration/template.py
iam/contrib/iam_migration/management/__init__.py
iam/contrib/iam_migration/management/commands/__init__.py
iam/contrib/iam_migration/management/commands/iam_makemigrations.py
iam/contrib/iam_migration/migrations/__init__.py
iam/contrib/iam_migration/utils/__init__.py
iam/contrib/iam_migration/utils/do_migrate.py
iam/contrib/tastypie/__init__.py
iam/contrib/tastypie/authorization.py
iam/contrib/tastypie/resource.py
iam/contrib/tastypie/shortcuts.py
iam/eval/__init__.py
iam/eval/constants.py
iam/eval/expression.py
iam/eval/object.py
iam/eval/operators.py
iam/model/__init__.py
iam/model/models.py
iam/resource/__init__.py
iam/resource/constants.py
iam/resource/dispatcher.py
iam/resource/provider.py
iam/resource/utils.py
tests/__init__.py
tests/test_collections.py
tests/test_exceptions.py
tests/test_iam.py
tests/test_meta.py
tests/test_shortcuts.py
tests/test_utils.py
tests/contrib/__init__.py
tests/contrib/converter/__init__.py
tests/contrib/converter/test_base.py
tests/contrib/converter/test_queryset.py
bk_iam-2.0.3.dist-info/METADATA
bk_iam-2.0.3.dist-info/WHEEL
bk_iam-2.0.3.dist-info/top_level.txt
bk_iam-2.0.3.dist-info/RECORD
