Metadata-Version: 2.4
Name: bk-iam
Version: 2.0.3
Summary: bk-iam python sdk
Home-page: https://github.com/TencentBlueKing/iam-python-sdk
Author: TencentBlueKing
Author-email: contactus_bk@tencent.com
Project-URL: Bug Tracker, https://github.com/TencentBlueKing/iam-python-sdk/issues
Classifier: Programming Language :: Python :: 3.6
Classifier: Programming Language :: Python :: 3.7
Classifier: Programming Language :: Python :: 3.8
Classifier: Programming Language :: Python :: 3.9
Classifier: Programming Language :: Python :: 3.10
Classifier: Programming Language :: Python :: 3.11
Classifier: License :: OSI Approved :: MIT License
Classifier: Operating System :: OS Independent
Requires-Python: >3, !=3.0.*, !=3.1.*, !=3.2.*, !=3.3.*, !=3.4.*, !=3.5.*, <4
Requires-Dist: six>=1.11.0
Requires-Dist: cachetools<6.0,>=3.1.1
Requires-Dist: requests>=2.16.0
Requires-Dist: curlify==2.2.1
Dynamic: author
Dynamic: author-email
Dynamic: classifier
Dynamic: description
Dynamic: description-content-type
Dynamic: home-page
Dynamic: project-url
Dynamic: requires-dist
Dynamic: requires-python
Dynamic: summary
